pixel_reshaper/__init__.py
pixel_reshaper/tools.py
pixel_reshaper-0.0.6.dist-info/LICENCE
pixel_reshaper-0.0.6.dist-info/METADATA
pixel_reshaper-0.0.6.dist-info/WHEEL
pixel_reshaper-0.0.6.dist-info/top_level.txt
pixel_reshaper-0.0.6.dist-info/RECORD
